flashkit/__init__.py
flashkit/cart.py
flashkit/device.py
flashkit/flashkit.py
flashkit-1.0.6.dist-info/METADATA
flashkit-1.0.6.dist-info/WHEEL
flashkit-1.0.6.dist-info/entry_points.txt
flashkit-1.0.6.dist-info/licenses/LICENSE.md
flashkit-1.0.6.dist-info/RECORD
