Metadata-Version: 2.1
Name: flashkit
Version: 1.0.6
Summary: Drive the Krikzz FlashKit Programmer MD to flash Sega Genesis carts from the command-line.
Project-URL: Homepage, https://github.com/joeyparrish/flashkit-md-py
Project-URL: Issues, https://github.com/joeyparrish/flashkit-md-py/issues
Author-email: Joey Parrish <joey.parrish@gmail.com>
License-File: LICENSE.md
Classifier: Development Status :: 5 - Production/Stable
Classifier: License :: OSI Approved :: GNU General Public License v3 (GPLv3)
Classifier: Operating System :: OS Independent
Classifier: Programming Language :: Python :: 3
Requires-Python: >=3.7
Requires-Dist: pyserial<4,>=3.5
